no996/__init__.py
no996/base/__init__.py
no996/base/config.py
no996/base/date.py
no996/base/db.py
no996/base/decorator.py
no996/base/dynamic.py
no996/base/file.py
no996/base/list.py
no996/plugins/__init__.py
no996/plugins/mq.py
no996-0.1.9.dist-info/METADATA
no996-0.1.9.dist-info/WHEEL
no996-0.1.9.dist-info/top_level.txt
no996-0.1.9.dist-info/RECORD
