Metadata-Version: 2.4
Name: no996
Version: 0.1.9
Summary: this use to work no996
Requires-Python: >=3.12
Requires-Dist: aio-pika>=9.5.0
Requires-Dist: arrow>=1.3.0
Requires-Dist: fastapi-structlog>=0.5.0
Requires-Dist: pandas>=2.2.3
Requires-Dist: psycopg[binary]<3.1.20,>=3.1.13
Requires-Dist: pydantic-settings>=2.6.1
Requires-Dist: pydantic[email,timezone]>=2.9.2
Requires-Dist: requests>=2.32.3
Requires-Dist: sqlmodel>=0.0.22
